odoo10_addon_attachment_action-10.0.1.0.0.99.dev3-py3.8-nspkg.pth
odoo/addons/attachment_action/README.rst
odoo/addons/attachment_action/__init__.py
odoo/addons/attachment_action/__manifest__.py
odoo/addons/attachment_action/i18n/attachment_action.pot
odoo/addons/attachment_action/readme/CONTRIBUTORS.rst
odoo/addons/attachment_action/readme/DESCRIPTION.rst
odoo/addons/attachment_action/readme/USAGE.rst
odoo/addons/attachment_action/static/description/icon.png
odoo/addons/attachment_action/static/description/index.html
odoo/addons/attachment_action/static/src/css/attachment_action.css
odoo/addons/attachment_action/static/src/xml/attachment_action.xml
odoo/addons/attachment_action/views/templates.xml
odoo10_addon_attachment_action-10.0.1.0.0.99.dev3.dist-info/METADATA
odoo10_addon_attachment_action-10.0.1.0.0.99.dev3.dist-info/WHEEL
odoo10_addon_attachment_action-10.0.1.0.0.99.dev3.dist-info/namespace_packages.txt
odoo10_addon_attachment_action-10.0.1.0.0.99.dev3.dist-info/top_level.txt
odoo10_addon_attachment_action-10.0.1.0.0.99.dev3.dist-info/RECORD
